LICENSE.txt
MANIFEST.in
README.rst
setup.py
nanodb_driver/__init__.py
nanodb_driver/driver.py
nanodb_driver.egg-info/PKG-INFO
nanodb_driver.egg-info/SOURCES.txt
nanodb_driver.egg-info/dependency_links.txt
nanodb_driver.egg-info/requires.txt
nanodb_driver.egg-info/top_level.txt
test/test_driver.py