Metadata-Version: 1.0
Name: nanodb_driver
Version: 0.0.3
Summary: Driver to interface application with a NanoDB server
Home-page: https://github.com/nano-db/nanodb_driver
Author: Pierre-Marie Dartus
Author-email: dartus.pierremarie@gmail.com
License: LICENSE.txt
Platform: UNKNOWN
